asciicut/__init__.py
asciicut/__main__.py
asciicut/schema.py
asciicut/utils.py
asciicut-0.1.2.dist-info/METADATA
asciicut-0.1.2.dist-info/WHEEL
asciicut-0.1.2.dist-info/entry_points.txt
asciicut-0.1.2.dist-info/RECORD
